AutoClean/__init__.py
AutoClean/autoclean.py
AutoClean/modules.py
py_AutoCleanRe-1.1.4.dist-info/LICENSE.txt
py_AutoCleanRe-1.1.4.dist-info/METADATA
py_AutoCleanRe-1.1.4.dist-info/WHEEL
py_AutoCleanRe-1.1.4.dist-info/top_level.txt
py_AutoCleanRe-1.1.4.dist-info/RECORD
