Metadata-Version: 2.1
Name: py-AutoCleanRe
Version: 1.1.4
Summary: AutoClean - Python Package for Automated Preprocessing & Cleaning of Datasets
License: MIT
Keywords: automated,cleaning,preprocessing,autoclean
Classifier: Development Status :: 5 - Production/Stable
Classifier: Intended Audience :: Developers
Classifier: Topic :: Software Development :: Build Tools
Classifier: License :: OSI Approved :: MIT License
Classifier: Programming Language :: Python :: 3.7
Classifier: Programming Language :: Python :: 3.8
Classifier: Programming Language :: Python :: 3.9
License-File: LICENSE.txt
Requires-Dist: scikit-learn
Requires-Dist: numpy
Requires-Dist: pandas
Requires-Dist: loguru
